docker_prune/__init__.py
docker_prune/cli.py
docker_prune/main.py
docker_prune/version.py
docker_prune/click_types/__init__.py
docker_prune/click_types/bytes.py
docker_prune/click_types/intrange.py
docker_prune/click_types/regex.py
docker_prune/click_types/timedelta.py
docker_prune/utils/__init__.py
docker_prune/utils/list.py
docker_prune-1.0.5.dist-info/METADATA
docker_prune-1.0.5.dist-info/WHEEL
docker_prune-1.0.5.dist-info/entry_points.txt
docker_prune-1.0.5.dist-info/licenses/LICENSE
docker_prune-1.0.5.dist-info/RECORD
