Metadata-Version: 2.4
Name: docker-prune
Version: 1.0.5
Summary: This tool is ideal for maintaining a clean, performant, and clutter-free Docker ecosystem.
Project-URL: Homepage, https://github.com/t4skforce/docker-prune
Project-URL: Source, https://github.com/t4skforce/docker-prune
Project-URL: Issues, https://github.com/t4skforce/docker-prune/issues
Author-email: t4skforce <7422037+t4skforce@users.noreply.github.com>
License-Expression: MIT
License-File: LICENSE
Classifier: Development Status :: 5 - Production/Stable
Classifier: Environment :: Other Environment
Classifier: Intended Audience :: Developers
Classifier: License :: OSI Approved :: MIT License
Classifier: Operating System :: OS Independent
Classifier: Programming Language :: Python
Classifier: Programming Language :: Python :: 3
Classifier: Programming Language :: Python :: 3.10
Classifier: Programming Language :: Python :: 3.11
Classifier: Programming Language :: Python :: 3.12
Classifier: Programming Language :: Python :: 3.13
Classifier: Topic :: Software Development
Classifier: Topic :: Utilities
Requires-Python: >=3.10
Requires-Dist: certifi>=2025.8.3
Requires-Dist: click>=8.2.1
Requires-Dist: docker>=7.1.0
Requires-Dist: jsonschema>=4.25.0
Requires-Dist: python-dateutil>=2.9.0
Requires-Dist: pyyaml>=6.0.2
